setup.py
ROPgadget4ROPGenerator.egg-info/PKG-INFO
ROPgadget4ROPGenerator.egg-info/SOURCES.txt
ROPgadget4ROPGenerator.egg-info/dependency_links.txt
ROPgadget4ROPGenerator.egg-info/top_level.txt
ropgadget/__init__.py
ropgadget/args.py
ropgadget/binary.py
ropgadget/core.py
ropgadget/gadgets.py
ropgadget/options.py
ropgadget/rgutils.py
ropgadget/updateAlert.py
ropgadget/version.py
ropgadget/loaders/__init__.py
ropgadget/loaders/elf.py
ropgadget/loaders/macho.py
ropgadget/loaders/pe.py
ropgadget/loaders/raw.py
ropgadget/loaders/universal.py
ropgadget/ropchain/__init__.py
ropgadget/ropchain/ropmaker.py
ropgadget/ropchain/arch/__init__.py
ropgadget/ropchain/arch/ropmakerx64.py
ropgadget/ropchain/arch/ropmakerx86.py
scripts/ROPgadget4ROPGenerator