Metadata-Version: 1.1
Name: ROPgadget4ROPGenerator
Version: 5.6.1
Summary: This is a python package of the famous ROPgadget tool version 5.6 used to support the ROPGenerator tool
Home-page: https://github.com/JonathanSalwan/ROPgadget
Author: Jonathan Salwan
Author-email: jonathan.salwan@gmail.com
License: BSD
Platform: UNKNOWN
Classifier: Topic :: Security
Classifier: Environment :: Console
Classifier: Operating System :: OS Independent
Classifier: License :: OSI Approved :: BSD License
Classifier: Programming Language :: Python :: 2.7
Classifier: Intended Audience :: Developers
